talk_summarizer/__init__.py
talk_summarizer/summarize_talk.py
talk_summarizer/utils.py
talk_summarizer-0.0.1.dist-info/LICENSE
talk_summarizer-0.0.1.dist-info/METADATA
talk_summarizer-0.0.1.dist-info/WHEEL
talk_summarizer-0.0.1.dist-info/top_level.txt
talk_summarizer-0.0.1.dist-info/RECORD
