Metadata-Version: 2.1
Name: talk-summarizer
Version: 0.0.1
Summary: Python library to summarize talks
Home-page: https://github.com/lawwu/talk-summarizer
Author: Lawrence Wu
License: Apache License, Version 2.0
Project-URL: Issues, https://github.com/lawwu/talk-summarizer/issues
Project-URL: CI, https://github.com/lawwu/talk-summarizer/actions
Project-URL: Changelog, https://github.com/lawwu/talk-summarizer/releases
Requires-Python: >=3.9
License-File: LICENSE
Requires-Dist: transformers
Requires-Dist: openai
Requires-Dist: openai-whisper
Requires-Dist: datasets
Requires-Dist: soundfile
Requires-Dist: librosa
Requires-Dist: ffmpeg-python
Requires-Dist: opencv-python
Requires-Dist: reportlab
Requires-Dist: pytest
Provides-Extra: test
Requires-Dist: pytest ; extra == 'test'
